llama_index/llms/gemini/__init__.py
llama_index/llms/gemini/base.py
llama_index/llms/gemini/py.typed
llama_index/llms/gemini/utils.py
llama_index_llms_gemini-0.6.0.dist-info/METADATA
llama_index_llms_gemini-0.6.0.dist-info/WHEEL
llama_index_llms_gemini-0.6.0.dist-info/licenses/LICENSE
llama_index_llms_gemini-0.6.0.dist-info/RECORD
